upm/__init__.py
upm/cli.py
upm/config.py
upm/template.py
upm/upm.py
upm_micro_project_manager-0.4.2.dist-info/LICENSE
upm_micro_project_manager-0.4.2.dist-info/METADATA
upm_micro_project_manager-0.4.2.dist-info/WHEEL
upm_micro_project_manager-0.4.2.dist-info/entry_points.txt
upm_micro_project_manager-0.4.2.dist-info/top_level.txt
upm_micro_project_manager-0.4.2.dist-info/RECORD
