Metadata-Version: 2.1
Name: upm---micro-project-manager
Version: 0.4.2
Summary: A simple project management system
Home-page: https://gitlab.com/rapp.jens/upm
Author: TecDroiD
Author-email: rapp.jens+pypi@gmail.com
License: BSD
Classifier: Development Status :: 3 - Alpha
Classifier: Intended Audience :: Developers
Classifier: License :: OSI Approved :: BSD License
Classifier: Operating System :: OS Independent
Classifier: Programming Language :: Python :: 3
Classifier: Programming Language :: Python :: 3.9
Classifier: Programming Language :: Python :: 3.11
Requires-Python: >=3.6
License-File: LICENSE
